alu_multi_cycle_memory.v
module alu_with_memory (
    input clk,                // Clock input
    input reset,              // Reset signal
    input [1:0] a,            // Operand A
    input [1:0] b,            // Operand B
    input [1:0] ctrl,         // Control signal
    input [1:0] reg_addr,     // Address to store result in register memory
    input reg_write,          // Write enable for register memory
    output reg [3:0] y,       // ALU output
    output reg c,             // Carry/Overflow flag
    output reg done,          // Done signal (indicating operation completion)
    output [3:0] reg_data     // Data of the selected register (for checking)
);

    // Register file: 4 registers, each 4 bits wide
    reg [3:0] reg_file [3:0];  // 4 registers of 4 bits each

    // States for the multicycle operation using localparams
    localparam FETCH = 2'b00;
    localparam EXECUTE = 2'b01;
    localparam WRITEBACK = 2'b10;

    reg [1:0] state, next_state;
    reg [1:0] a_reg, b_reg;
    reg [1:0] ctrl_reg;

    // Register memory read output (for checking the value of the register)
    assign reg_data = reg_file[reg_addr];

    always @(posedge clk or posedge reset) begin
        if (reset) begin
            state <= FETCH;
            done <= 0;
            c <= 0;
            y <= 0;
            // Initialize register file to zero
            reg_file[0] <= 4'b0000;
            reg_file[1] <= 4'b0000;
            reg_file[2] <= 4'b0000;
            reg_file[3] <= 4'b0000;
        end else begin
            state <= next_state;
        end
    end

    always @(*) begin
        // Default values for outputs
        done = 0;
        next_state = state; // Keep current state unless changed
        case (state)
            FETCH: begin
                // Fetch stage - capture inputs and prepare for execution
                a_reg = a;
                b_reg = b;
                ctrl_reg = ctrl;
                next_state = EXECUTE;  // Move to execute
            end
            EXECUTE: begin
                // Execute stage - perform ALU operation
                case (ctrl_reg)
                    2'b00: begin // Add
                        {c, y} = a_reg + b_reg; 
                    end
                    2'b01: begin // Subtract
                        {c, y} = a_reg - b_reg; 
                    end
                    2'b10: begin // Multiply
                        y = a_reg * b_reg; 
                        c = 0; // No overflow
                    end
                    2'b11: begin // Divide
                        if (b_reg != 0) begin
                            y = a_reg / b_reg; 
                            c = 0; // No error
                        end else begin
                            y = 4'b0000; 
                            c = 1; // Error due to division by zero
                        end
                    end
                    default: begin
                        y = 4'b0000; 
                        c = 0;
                    end
                endcase
                next_state = WRITEBACK;  // Move to write-back stage
            end
            WRITEBACK: begin
                // Write-back stage - store result in the register memory if write enable is active
                if (reg_write) begin
                    reg_file[reg_addr] <= y;  // Store ALU result in selected register
                end
                done = 1;  // Signal that operation is complete
                next_state = FETCH;  // Return to fetch state for next operation
            end
            default: begin
                next_state = FETCH;
            end
        endcase
    end

endmodule

alu_multi_cycle_memory_adarsh_tb.v
module tb_alu_with_memory;

    reg clk;
    reg reset;
    reg [1:0] a;   
    reg [1:0] b;          
    reg [1:0] ctrl;      
    reg [1:0] reg_addr;   // Register address to store result
    reg reg_write;         // Write enable for register
    wire [3:0] y;        
    wire c;              
    wire done;           // Done signal from the ALU
    wire [3:0] reg_data; // Data of the selected register

    // Instantiate the ALU with register memory
    alu_with_memory uut (
        .clk(clk),
        .reset(reset),
        .a(a),
        .b(b),
        .ctrl(ctrl),
        .reg_addr(reg_addr),
        .reg_write(reg_write),
        .y(y),
        .c(c),
        .done(done),
        .reg_data(reg_data)
    );

    // Clock generation
    always begin
        #5 clk = ~clk;  // Generate clock with a period of 10
    end

    // Test cases
    initial begin
        // Initial setup
        $dumpfile("alu_with_memory_test.vcd");
        $dumpvars(0, tb_alu_with_memory);

        clk = 0;
        reset = 1;
        a = 2'b10;
        b = 2'b01;
        ctrl = 2'b00;  // ADD
        reg_addr = 2'b00;
        reg_write = 0;
        #30 reset = 0; // Release reset

        // Test ADD operation and store result in register 0
        #30 reg_write = 1; // Enable write to register 0
        a = 2'b10; b = 2'b01; ctrl = 2'b00;  // ADD (2 + 1 = 3)
        #30;
        reg_write = 0; // Disable write to register

        // Check if register 0 contains the result
        #30;
        $display("Register 0: %b", reg_data); // Should display 3 (00000011)

        // Test SUBTRACT operation and store result in register 1
        #30 reg_write = 1;
        a = 2'b10; b = 2'b01; ctrl = 2'b01;  // SUBTRACT (2 - 1 = 1)
        reg_addr = 2'b01; // Store result in register 1
        #30;
        reg_write = 0;

        // Check if register 1 contains the result
        #30;
        $display("Register 1: %b", reg_data); // Should display 1 (00000001)

        // Finish simulation
        $finish;
    end
endmodule

alu_with_memory_test.vcd
$date
	Thu Nov 21 19:30:44 2024
$end
$version
	Icarus Verilog
$end
$timescale
	1s
$end
$scope module tb_alu_with_memory $end
$var wire 4 ! y [3:0] $end
$var wire 4 " reg_data [3:0] $end
$var wire 1 # done $end
$var wire 1 $ c $end
$var reg 2 % a [1:0] $end
$var reg 2 & b [1:0] $end
$var reg 1 ' clk $end
$var reg 2 ( ctrl [1:0] $end
$var reg 2 ) reg_addr [1:0] $end
$var reg 1 * reg_write $end
$var reg 1 + reset $end
$scope module uut $end
$var wire 2 , a [1:0] $end
$var wire 2 - b [1:0] $end
$var wire 1 ' clk $end
$var wire 2 . ctrl [1:0] $end
$var wire 2 / reg_addr [1:0] $end
$var wire 4 0 reg_data [3:0] $end
$var wire 1 * reg_write $end
$var wire 1 + reset $end
$var parameter 2 1 EXECUTE $end
$var parameter 2 2 FETCH $end
$var parameter 2 3 WRITEBACK $end
$var reg 2 4 a_reg [1:0] $end
$var reg 2 5 b_reg [1:0] $end
$var reg 1 $ c $end
$var reg 2 6 ctrl_reg [1:0] $end
$var reg 1 # done $end
$var reg 2 7 next_state [1:0] $end
$var reg 2 8 state [1:0] $end
$var reg 4 9 y [3:0] $end
$upscope $end
$upscope $end
$enddefinitions $end
$comment Show the parameter values. $end
$dumpall
b10 3
b0 2
b1 1
$end
#0
$dumpvars
b0 9
b0 8
b1 7
b0 6
b1 5
b10 4
b0 0
b0 /
b0 .
b1 -
b10 ,
1+
0*
b0 )
b0 (
0'
b1 &
b10 %
0$
0#
b0 "
b0 !
$end
#5
1'
#10
0'
#15
1'
#20
0'
#25
1'
#30
0'
0+
#35
b10 7
b11 !
b11 9
b1 8
1'
#40
0'
#45
b0 7
1#
b10 8
1'
#50
0'
#55
b1 7
0#
b0 8
1'
#60
b1 7
0'
1*
#65
b10 7
b1 8
1'
#70
0'
#75
b11 "
b11 0
b0 7
1#
b10 8
1'
#80
0'
#85
b1 7
0#
b0 8
1'
#90
b1 7
0'
0*
#95
b10 7
b1 8
1'
#100
0'
#105
b0 7
1#
b10 8
1'
#110
0'
#115
b1 7
0#
b0 8
1'
#120
0'
#125
b10 7
b1 8
1'
#130
0'
#135
b0 7
1#
b10 8
1'
#140
0'
#145
b1 7
0#
b0 8
1'
#150
b1 6
b1 7
0'
b0 "
b0 0
b1 )
b1 /
b1 (
b1 .
1*
#155
b10 7
b1 !
b1 9
b1 8
1'
#160
0'
#165
b1 "
b1 0
b0 7
1#
b10 8
1'
#170
0'
#175
b1 7
0#
b0 8
1'
#180
b1 7
0'
0*
#185
b10 7
b1 8
1'
#190
0'
#195
b0 7
1#
b10 8
1'
#200
0'
#205
b1 7
0#
b0 8
1'
