alu_multi_cycle.v
module au(
    input clk,            // Clock input
    input reset,          // Reset signal
    input [1:0] a,        // Operand A
    input [1:0] b,        // Operand B
    input [1:0] ctrl,     // Control signal
    output reg [3:0] y,   // ALU output
    output reg c,         // Carry/Overflow flag
    output reg done       // Done signal (indicating operation completion)
);

    // States for the multicycle operation using localparams
    localparam FETCH = 2'b00;
    localparam EXECUTE = 2'b01;
    localparam WRITEBACK = 2'b10;

    reg [1:0] state, next_state;
    reg [1:0] a_reg, b_reg;
    reg [1:0] ctrl_reg;

    always @(posedge clk or posedge reset) begin
        if (reset) begin
            state <= FETCH;
            done <= 0;
            c <= 0;
            y <= 0;
        end else begin
            state <= next_state;
        end
    end

    always @(*) begin
        // Default values for outputs
        done = 0;
        next_state = state; // Keep current state unless changed
        case (state)
            FETCH: begin
                // Fetch stage - capture inputs and prepare for execution
                a_reg = a;
                b_reg = b;
                ctrl_reg = ctrl;
                next_state = EXECUTE;  // Move to execute
            end
            EXECUTE: begin
                // Execute stage - perform ALU operation
                case (ctrl_reg)
                    2'b00: begin // Add
                        {c, y} = a_reg + b_reg; 
                    end
                    2'b01: begin // Subtract
                        {c, y} = a_reg - b_reg; 
                    end
                    2'b10: begin // Multiply
                        y = a_reg * b_reg; 
                        c = 0; // No overflow
                    end
                    2'b11: begin // Divide
                        if (b_reg != 0) begin
                            y = a_reg / b_reg; 
                            c = 0; // No error
                        end else begin
                            y = 4'b0000; 
                            c = 1; // Error due to division by zero
                        end
                    end
                    default: begin
                        y = 4'b0000; 
                        c = 0;
                    end
                endcase
                next_state = WRITEBACK;  // Move to write-back stage
            end
            WRITEBACK: begin
                // Write-back stage - set done flag and reset outputs
                done = 1;  // Signal that operation is complete
                next_state = FETCH;  // Return to fetch state for next operation
            end
            default: begin
                next_state = FETCH;
            end
        endcase
    end

endmodule

alu_multi_cycle_adarsh_tb.v
module tb_au;

    reg clk;
    reg reset;
    reg [1:0] a;   
    reg [1:0] b;          
    reg [1:0] ctrl;      
    wire [3:0] y;        
    wire c;              
    wire done;           // Done signal from the ALU

    // Instantiate the ALU module
    au uut (
        .clk(clk),
        .reset(reset),
        .a(a),
        .b(b),
        .ctrl(ctrl),
        .y(y),
        .c(c),
        .done(done)
    );

    // Clock generation
    always begin
        #5 clk = ~clk;  // Generate clock with a period of 10
    end

    // Test cases
    initial begin
        // Initial setup
        $dumpfile("au_test.vcd");
        $dumpvars(0, tb_au);

        clk = 0;
        reset = 1;
        a = 2'b10;
        b = 2'b01;
        ctrl = 2'b00;  // ADD
        #30 reset = 0; // Release reset

        // Test ADD operation
        #30;
        a = 2'b10; b = 2'b01; ctrl = 2'b00;  // ADD (2 + 1 = 3)
        #30;  // Wait for the operation to complete

        // Test SUBTRACT operation
        a = 2'b10; b = 2'b01; ctrl = 2'b01;  // SUBTRACT (2 - 1 = 1)
        #30;

        // Test MULTIPLY operation
        a = 2'b10; b = 2'b10; ctrl = 2'b10;  // MULTIPLY (2 * 2 = 4)
        #30;

        // Test DIVIDE operation
        a = 2'b10; b = 2'b01; ctrl = 2'b11;  // DIVIDE (2 / 1 = 2)
        #30;

        // Test DIVIDE by zero
        a = 2'b10; b = 2'b00; ctrl = 2'b11;  // DIVIDE by 0 (should signal error)
        #30;

        $finish;
    end
endmodule

au_test_yash.vcd
$date
	Fri Nov 22 12:43:09 2024
$end
$version
	Icarus Verilog
$end
$timescale
	1s
$end
$scope module tb_au $end
$var wire 4 ! y [3:0] $end
$var wire 1 " done $end
$var wire 1 # c $end
$var reg 2 $ a [1:0] $end
$var reg 2 % b [1:0] $end
$var reg 1 & clk $end
$var reg 2 ' ctrl [1:0] $end
$var reg 1 ( reset $end
$scope module uut $end
$var wire 2 ) a [1:0] $end
$var wire 2 * b [1:0] $end
$var wire 1 & clk $end
$var wire 2 + ctrl [1:0] $end
$var wire 1 ( reset $end
$var parameter 2 , EXECUTE $end
$var parameter 2 - FETCH $end
$var parameter 2 . WRITEBACK $end
$var reg 2 / a_reg [1:0] $end
$var reg 2 0 b_reg [1:0] $end
$var reg 1 # c $end
$var reg 2 1 ctrl_reg [1:0] $end
$var reg 1 " done $end
$var reg 2 2 next_state [1:0] $end
$var reg 2 3 state [1:0] $end
$var reg 4 4 y [3:0] $end
$upscope $end
$upscope $end
$enddefinitions $end
$comment Show the parameter values. $end
$dumpall
b10 .
b0 -
b1 ,
$end
#0
$dumpvars
b0 4
b0 3
b1 2
b0 1
b1 0
b10 /
b0 +
b1 *
b10 )
1(
b0 '
0&
b1 %
b10 $
0#
0"
b0 !
$end
#11
b10 2
b11 !
b11 4
b1 3
0(
1&
#22
0&
#33
b0 2
1"
b10 3
1&
#43
b0 2
1"
b1 '
b1 +
b11 $
b11 )
#44
0&
#55
b1 2
b1 1
b11 /
0"
b0 3
1&
#64
b10 1
b11 0
b10 /
b1 2
b10 '
b10 +
b11 %
b11 *
b10 $
b10 )
#66
0&
#77
b10 2
b110 !
b110 4
b1 3
1&
#85
b10 2
b11 '
b11 +
b1 %
b1 *
#88
0&
#99
b0 2
1"
b10 3
1&
#106
b0 2
1"
b0 %
b0 *
#110
0&
#121
b1 2
b11 1
b0 0
0"
b0 3
1&
