fulladder.v
module fulladder(
	input a,b,ci,
	output s,co,x,y,z,m,n
	);
	xor(n,a,b);
	xor(s,n,ci);
	and(x,a,b);
	and(y,b,ci);
	and(z,ci,a);
	or(m,x,y);
	or(co,m,z);
	endmodule

fulladder_tb.v
module fulladder_test;
reg a,b,ci;
wire s,co;
fulladder uut(
.a(a),
.b(b),
.ci(ci),
.s(s),
.co(co),
.x(x),
.y(y),
.z(z),
.m(m),
.n(n)
);
initial begin 
$dumpfile("fulladder.vcd");
$dumpvars(0,fulladder_test);
a=0;b=0;ci=0;
#9
a=0;b=0;ci=1;
#9
a=0;b=1;ci=0;
#9
a=0;b=1;ci=1;
#9
a=1;b=0;ci=0;
#9
a=1;b=0;ci=1;
#9
a=1;b=1;ci=0;
#9
a=1;b=1;ci=1;
#9
$finish();
end
endmodule

fulladder.vcd
$date
	Mon Sep 09 18:49:41 2024
$end
$version
	Icarus Verilog
$end
$timescale
	1s
$end
$scope module fulladder_test $end
$var wire 1 ! z $end
$var wire 1 " y $end
$var wire 1 # x $end
$var wire 1 $ s $end
$var wire 1 % n $end
$var wire 1 & m $end
$var wire 1 ' co $end
$var reg 1 ( a $end
$var reg 1 ) b $end
$var reg 1 * ci $end
$scope module uut $end
$var wire 1 ( a $end
$var wire 1 ) b $end
$var wire 1 * ci $end
$var wire 1 ' co $end
$var wire 1 & m $end
$var wire 1 % n $end
$var wire 1 $ s $end
$var wire 1 # x $end
$var wire 1 " y $end
$var wire 1 ! z $end
$upscope $end
$upscope $end
$enddefinitions $end
$comment Show the parameter values. $end
$dumpall
$end
#0
$dumpvars
0*
0)
0(
0'
0&
0%
0$
0#
0"
0!
$end
#9
1$
1*
#18
1%
0*
1)
#27
1'
1&
0$
1"
1*
#36
0'
0&
1$
0"
0*
0)
1(
#45
1'
0$
1!
1*
#54
1&
0!
0%
1#
0*
1)
#63
1$
1"
1!
1*
